db_connector/__init__.py
db_connector/db_connector.py
db_connector_kr-0.1.5.dist-info/LICENSE
db_connector_kr-0.1.5.dist-info/METADATA
db_connector_kr-0.1.5.dist-info/WHEEL
db_connector_kr-0.1.5.dist-info/top_level.txt
db_connector_kr-0.1.5.dist-info/RECORD
