Metadata-Version: 2.1
Name: db-connector-kr
Version: 0.1.5
Summary: A Python library for connecting to various databases.
Home-page: https://github.com/lim39/dbconnector
Author: Sanggu Lim
Author-email: data.ai.lim39@gmail.com
Classifier: Programming Language :: Python :: 3
Classifier: License :: OSI Approved :: MIT License
Classifier: Operating System :: OS Independent
Requires-Python: >=3.7
License-File: LICENSE
Requires-Dist: pandas
Requires-Dist: snowflake-connector-python
Requires-Dist: pymysql
Provides-Extra: postgres
Requires-Dist: psycopg2-binary; extra == "postgres"
